wizedispatcher/__init__.py
wizedispatcher/core.py
wizedispatcher-0.1.1.dist-info/licenses/LICENSE
wizedispatcher-0.1.1.dist-info/wizedispatcher/__init__.py
wizedispatcher-0.1.1.dist-info/wizedispatcher/core.py
wizedispatcher-0.1.1.dist-info/METADATA
wizedispatcher-0.1.1.dist-info/WHEEL
wizedispatcher-0.1.1.dist-info/top_level.txt
wizedispatcher-0.1.1.dist-info/RECORD
