Metadata-Version: 2.4
Name: wizedispatcher
Version: 0.1.1
Summary: Runtime dispatch with decorator-based overload registration.
Home-page: https://github.com/kairos-xx/wizedispatcher
Author: Joao Lopes
Author-email: Joao Lopes <joaoslopes@gmail.com>
License: MIT License
Project-URL: Homepage, https://github.com/kairos-xx/wizedispatcher
Project-URL: Documentation, https://github.com/kairos-xx/wizedispatcher/wiki
Project-URL: Repository, https://github.com/kairos-xx/wizedispatcher.git
Project-URL: Issues, https://github.com/kairos-xx/wizedispatcher/issues
Keywords: dispatch,overload,typing,decorator
Classifier: Programming Language :: Python :: 3
Classifier: Programming Language :: Python :: 3 :: Only
Classifier: Programming Language :: Python :: 3.10
Classifier: Programming Language :: Python :: 3.11
Classifier: Programming Language :: Python :: 3.12
Classifier: Programming Language :: Python :: 3.13
Classifier: License :: OSI Approved :: MIT License
Classifier: Intended Audience :: Developers
Classifier: Topic :: Software Development :: Libraries
Requires-Python: >=3.9
License-File: LICENSE
Provides-Extra: dev
Requires-Dist: pytest>=7; extra == "dev"
Requires-Dist: ruff>=0.5; extra == "dev"
Requires-Dist: mypy>=1.11; extra == "dev"
Dynamic: author
Dynamic: home-page
Dynamic: license-file
Dynamic: requires-python
